randomagent/__init__.py
randomagent/useragents.py
randomagent-0.0.1.dist-info/METADATA
randomagent-0.0.1.dist-info/WHEEL
randomagent-0.0.1.dist-info/top_level.txt
randomagent-0.0.1.dist-info/RECORD
