Metadata-Version: 2.4
Name: randomagent
Version: 0.0.1
Summary: gets random useragent
Author-email: k144 <author@example.com>
License-Expression: MIT
Classifier: Programming Language :: Python :: 3
Classifier: Operating System :: OS Independent
Requires-Python: >=3.13
Requires-Dist: notebook>=7.4.5
